st_user_info_panel/__init__.py
st_user_info_panel/frontend/index.html
st_user_info_panel/frontend/main.js
st_user_info_panel/frontend/streamlit-component-lib.js
st_user_info_panel/frontend/style.css
st_user_info_panel-0.1.0.dist-info/LICENSE
st_user_info_panel-0.1.0.dist-info/METADATA
st_user_info_panel-0.1.0.dist-info/WHEEL
st_user_info_panel-0.1.0.dist-info/RECORD
