Metadata-Version: 2.3
Name: st-user-info-panel
Version: 0.1.0
Summary: Streamlit component for a floating User Info panel anchored to the sidebar. Supports fixed float stick in sidebar, a collapsed avatar chip when the sidebar is hidden, usage stats (messages/tokens/cost), and compact layout.
Author: agustyawan-arif
Author-email: arifagustyawan@gmail.com
Requires-Python: >=3.11
Classifier: Programming Language :: Python :: 3
Classifier: Programming Language :: Python :: 3.11
Classifier: Programming Language :: Python :: 3.12
Classifier: Programming Language :: Python :: 3.13
Requires-Dist: streamlit (>=1.48.1,<2.0.0)
Project-URL: Homepage, https://github.com/agustyawan-arif/st-user-info-panel
Project-URL: Issues, https://github.com/agustyawan-arif/st-user-info-panel/issues
Project-URL: Repository, https://github.com/agustyawan-arif/st-user-info-panel
